{
  "version": 1,
  "runs": [
    {
      "at": "2026-05-02T01:13:45.354Z",
      "sha": "e47c4caffdfffd49efe6afac854e81bdef12dc8c",
      "pr": null,
      "actor": "braedonsaunders",
      "files": 853,
      "functions": 12449,
      "loc": 467661,
      "languages": 19,
      "topLanguages": [
        {
          "ext": "py",
          "pct": 76,
          "lines": 355854
        },
        {
          "ext": "tsx",
          "pct": 17,
          "lines": 78651
        },
        {
          "ext": "json",
          "pct": 3,
          "lines": 12990
        },
        {
          "ext": "ts",
          "pct": 3,
          "lines": 11717
        },
        {
          "ext": "md",
          "pct": 1,
          "lines": 3382
        }
      ],
      "dead": 109,
      "deadPct": 0.9,
      "circular": 1,
      "godObjects": 1,
      "avgCoupling": 8.4,
      "securityIssues": 69,
      "patterns": 12,
      "duplicates": 99,
      "layerViolations": 1401,
      "connections": 7207,
      "avgFnLines": 10.9,
      "longestFn": 16,
      "testFiles": 186,
      "testRatio": 21.8,
      "topFolders": [
        {
          "name": "backend",
          "count": 679
        },
        {
          "name": "frontend",
          "count": 141
        },
        {
          "name": "scripts",
          "count": 20
        },
        {
          "name": "root",
          "count": 7
        },
        {
          "name": "docs",
          "count": 3
        }
      ],
      "folders": 5,
      "grade": "D",
      "score": 60,
      "topBlast": {
        "path": "backend/services/strategy_helpers/persistent_state.py",
        "direct": 474,
        "transitive": 734,
        "total": 1208
      },
      "fragility": [
        {
          "path": "backend/services/strategy_helpers/persistent_state.py",
          "direct": 474,
          "transitive": 734,
          "total": 1208
        },
        {
          "path": "backend/tests/test_trader_orchestrator_worker.py",
          "direct": 303,
          "transitive": 730,
          "total": 1033
        },
        {
          "path": "backend/models/database.py",
          "direct": 199,
          "transitive": 730,
          "total": 929
        }
      ]
    },
    {
      "at": "2026-05-02T01:27:01.809Z",
      "sha": "caf14c4ea939df3942229ad1435af403465ac235",
      "pr": null,
      "actor": "braedonsaunders",
      "files": 853,
      "functions": 12449,
      "loc": 467690,
      "languages": 19,
      "topLanguages": [
        {
          "ext": "py",
          "pct": 76,
          "lines": 355883
        },
        {
          "ext": "tsx",
          "pct": 17,
          "lines": 78651
        },
        {
          "ext": "json",
          "pct": 3,
          "lines": 12990
        },
        {
          "ext": "ts",
          "pct": 3,
          "lines": 11717
        },
        {
          "ext": "md",
          "pct": 1,
          "lines": 3382
        }
      ],
      "dead": 109,
      "deadPct": 0.9,
      "circular": 1,
      "godObjects": 1,
      "avgCoupling": 8.4,
      "securityIssues": 69,
      "patterns": 12,
      "duplicates": 99,
      "layerViolations": 1401,
      "connections": 7207,
      "avgFnLines": 10.9,
      "longestFn": 16,
      "testFiles": 186,
      "testRatio": 21.8,
      "topFolders": [
        {
          "name": "backend",
          "count": 679
        },
        {
          "name": "frontend",
          "count": 141
        },
        {
          "name": "scripts",
          "count": 20
        },
        {
          "name": "root",
          "count": 7
        },
        {
          "name": "docs",
          "count": 3
        }
      ],
      "folders": 5,
      "grade": "D",
      "score": 60,
      "topBlast": {
        "path": "backend/services/strategy_helpers/persistent_state.py",
        "direct": 474,
        "transitive": 734,
        "total": 1208
      },
      "fragility": [
        {
          "path": "backend/services/strategy_helpers/persistent_state.py",
          "direct": 474,
          "transitive": 734,
          "total": 1208
        },
        {
          "path": "backend/tests/test_trader_orchestrator_worker.py",
          "direct": 303,
          "transitive": 730,
          "total": 1033
        },
        {
          "path": "backend/models/database.py",
          "direct": 199,
          "transitive": 730,
          "total": 929
        }
      ]
    },
    {
      "at": "2026-05-02T01:39:26.775Z",
      "sha": "cbdb6b46f4a3472f6799cc9b50a202574e2d2194",
      "pr": null,
      "actor": "braedonsaunders",
      "files": 854,
      "functions": 12451,
      "loc": 467747,
      "languages": 19,
      "topLanguages": [
        {
          "ext": "py",
          "pct": 76,
          "lines": 355940
        },
        {
          "ext": "tsx",
          "pct": 17,
          "lines": 78651
        },
        {
          "ext": "json",
          "pct": 3,
          "lines": 12990
        },
        {
          "ext": "ts",
          "pct": 3,
          "lines": 11717
        },
        {
          "ext": "md",
          "pct": 1,
          "lines": 3382
        }
      ],
      "dead": 109,
      "deadPct": 0.9,
      "circular": 1,
      "godObjects": 1,
      "avgCoupling": 8.4,
      "securityIssues": 69,
      "patterns": 12,
      "duplicates": 99,
      "layerViolations": 1402,
      "connections": 7208,
      "avgFnLines": 10.9,
      "longestFn": 16,
      "testFiles": 186,
      "testRatio": 21.8,
      "topFolders": [
        {
          "name": "backend",
          "count": 680
        },
        {
          "name": "frontend",
          "count": 141
        },
        {
          "name": "scripts",
          "count": 20
        },
        {
          "name": "root",
          "count": 7
        },
        {
          "name": "docs",
          "count": 3
        }
      ],
      "folders": 5,
      "grade": "D",
      "score": 60,
      "topBlast": {
        "path": "backend/services/strategy_helpers/persistent_state.py",
        "direct": 474,
        "transitive": 735,
        "total": 1209
      },
      "fragility": [
        {
          "path": "backend/services/strategy_helpers/persistent_state.py",
          "direct": 474,
          "transitive": 735,
          "total": 1209
        },
        {
          "path": "backend/tests/test_trader_orchestrator_worker.py",
          "direct": 304,
          "transitive": 731,
          "total": 1035
        },
        {
          "path": "backend/models/database.py",
          "direct": 199,
          "transitive": 731,
          "total": 930
        }
      ]
    },
    {
      "at": "2026-05-02T01:51:49.143Z",
      "sha": "7d86db5c8df09bea6abce62ac1b95e843e83d78b",
      "pr": null,
      "actor": "braedonsaunders",
      "files": 855,
      "functions": 12453,
      "loc": 467814,
      "languages": 19,
      "topLanguages": [
        {
          "ext": "py",
          "pct": 76,
          "lines": 356007
        },
        {
          "ext": "tsx",
          "pct": 17,
          "lines": 78651
        },
        {
          "ext": "json",
          "pct": 3,
          "lines": 12990
        },
        {
          "ext": "ts",
          "pct": 3,
          "lines": 11717
        },
        {
          "ext": "md",
          "pct": 1,
          "lines": 3382
        }
      ],
      "dead": 109,
      "deadPct": 0.9,
      "circular": 1,
      "godObjects": 1,
      "avgCoupling": 8.4,
      "securityIssues": 69,
      "patterns": 12,
      "duplicates": 99,
      "layerViolations": 1403,
      "connections": 7209,
      "avgFnLines": 10.9,
      "longestFn": 16,
      "testFiles": 186,
      "testRatio": 21.8,
      "topFolders": [
        {
          "name": "backend",
          "count": 681
        },
        {
          "name": "frontend",
          "count": 141
        },
        {
          "name": "scripts",
          "count": 20
        },
        {
          "name": "root",
          "count": 7
        },
        {
          "name": "docs",
          "count": 3
        }
      ],
      "folders": 5,
      "grade": "D",
      "score": 60,
      "topBlast": {
        "path": "backend/services/strategy_helpers/persistent_state.py",
        "direct": 474,
        "transitive": 736,
        "total": 1210
      },
      "fragility": [
        {
          "path": "backend/services/strategy_helpers/persistent_state.py",
          "direct": 474,
          "transitive": 736,
          "total": 1210
        },
        {
          "path": "backend/tests/test_trader_orchestrator_worker.py",
          "direct": 305,
          "transitive": 732,
          "total": 1037
        },
        {
          "path": "backend/models/database.py",
          "direct": 199,
          "transitive": 732,
          "total": 931
        }
      ]
    },
    {
      "at": "2026-05-02T02:05:04.534Z",
      "sha": "d195e4d540772445032efec67a1e94f12c5d0c04",
      "pr": null,
      "actor": "braedonsaunders",
      "files": 855,
      "functions": 12453,
      "loc": 467836,
      "languages": 19,
      "topLanguages": [
        {
          "ext": "py",
          "pct": 76,
          "lines": 356029
        },
        {
          "ext": "tsx",
          "pct": 17,
          "lines": 78651
        },
        {
          "ext": "json",
          "pct": 3,
          "lines": 12990
        },
        {
          "ext": "ts",
          "pct": 3,
          "lines": 11717
        },
        {
          "ext": "md",
          "pct": 1,
          "lines": 3382
        }
      ],
      "dead": 109,
      "deadPct": 0.9,
      "circular": 1,
      "godObjects": 1,
      "avgCoupling": 8.4,
      "securityIssues": 69,
      "patterns": 12,
      "duplicates": 99,
      "layerViolations": 1403,
      "connections": 7209,
      "avgFnLines": 10.9,
      "longestFn": 16,
      "testFiles": 186,
      "testRatio": 21.8,
      "topFolders": [
        {
          "name": "backend",
          "count": 681
        },
        {
          "name": "frontend",
          "count": 141
        },
        {
          "name": "scripts",
          "count": 20
        },
        {
          "name": "root",
          "count": 7
        },
        {
          "name": "docs",
          "count": 3
        }
      ],
      "folders": 5,
      "grade": "D",
      "score": 60,
      "topBlast": {
        "path": "backend/services/strategy_helpers/persistent_state.py",
        "direct": 474,
        "transitive": 736,
        "total": 1210
      },
      "fragility": [
        {
          "path": "backend/services/strategy_helpers/persistent_state.py",
          "direct": 474,
          "transitive": 736,
          "total": 1210
        },
        {
          "path": "backend/tests/test_trader_orchestrator_worker.py",
          "direct": 305,
          "transitive": 732,
          "total": 1037
        },
        {
          "path": "backend/models/database.py",
          "direct": 199,
          "transitive": 732,
          "total": 931
        }
      ]
    },
    {
      "at": "2026-05-02T02:17:04.918Z",
      "sha": "48910c1f7416dc69fd165f541cb0343f289e6d5f",
      "pr": null,
      "actor": "braedonsaunders",
      "files": 855,
      "functions": 12453,
      "loc": 467869,
      "languages": 19,
      "topLanguages": [
        {
          "ext": "py",
          "pct": 76,
          "lines": 356062
        },
        {
          "ext": "tsx",
          "pct": 17,
          "lines": 78651
        },
        {
          "ext": "json",
          "pct": 3,
          "lines": 12990
        },
        {
          "ext": "ts",
          "pct": 3,
          "lines": 11717
        },
        {
          "ext": "md",
          "pct": 1,
          "lines": 3382
        }
      ],
      "dead": 109,
      "deadPct": 0.9,
      "circular": 1,
      "godObjects": 1,
      "avgCoupling": 8.4,
      "securityIssues": 69,
      "patterns": 12,
      "duplicates": 99,
      "layerViolations": 1403,
      "connections": 7209,
      "avgFnLines": 10.9,
      "longestFn": 16,
      "testFiles": 186,
      "testRatio": 21.8,
      "topFolders": [
        {
          "name": "backend",
          "count": 681
        },
        {
          "name": "frontend",
          "count": 141
        },
        {
          "name": "scripts",
          "count": 20
        },
        {
          "name": "root",
          "count": 7
        },
        {
          "name": "docs",
          "count": 3
        }
      ],
      "folders": 5,
      "grade": "D",
      "score": 60,
      "topBlast": {
        "path": "backend/services/strategy_helpers/persistent_state.py",
        "direct": 474,
        "transitive": 736,
        "total": 1210
      },
      "fragility": [
        {
          "path": "backend/services/strategy_helpers/persistent_state.py",
          "direct": 474,
          "transitive": 736,
          "total": 1210
        },
        {
          "path": "backend/tests/test_trader_orchestrator_worker.py",
          "direct": 305,
          "transitive": 732,
          "total": 1037
        },
        {
          "path": "backend/models/database.py",
          "direct": 199,
          "transitive": 732,
          "total": 931
        }
      ]
    },
    {
      "at": "2026-05-02T02:54:09.459Z",
      "sha": "afa1cb56d0ba04ca0643b46cefe72516a1bc02ba",
      "pr": null,
      "actor": "braedonsaunders",
      "files": 855,
      "functions": 12458,
      "loc": 467974,
      "languages": 19,
      "topLanguages": [
        {
          "ext": "py",
          "pct": 76,
          "lines": 356167
        },
        {
          "ext": "tsx",
          "pct": 17,
          "lines": 78651
        },
        {
          "ext": "json",
          "pct": 3,
          "lines": 12990
        },
        {
          "ext": "ts",
          "pct": 3,
          "lines": 11717
        },
        {
          "ext": "md",
          "pct": 1,
          "lines": 3382
        }
      ],
      "dead": 109,
      "deadPct": 0.9,
      "circular": 1,
      "godObjects": 1,
      "avgCoupling": 8.4,
      "securityIssues": 69,
      "patterns": 12,
      "duplicates": 99,
      "layerViolations": 1403,
      "connections": 7210,
      "avgFnLines": 10.9,
      "longestFn": 16,
      "testFiles": 186,
      "testRatio": 21.8,
      "topFolders": [
        {
          "name": "backend",
          "count": 681
        },
        {
          "name": "frontend",
          "count": 141
        },
        {
          "name": "scripts",
          "count": 20
        },
        {
          "name": "root",
          "count": 7
        },
        {
          "name": "docs",
          "count": 3
        }
      ],
      "folders": 5,
      "grade": "D",
      "score": 60,
      "topBlast": {
        "path": "backend/services/strategy_helpers/persistent_state.py",
        "direct": 474,
        "transitive": 736,
        "total": 1210
      },
      "fragility": [
        {
          "path": "backend/services/strategy_helpers/persistent_state.py",
          "direct": 474,
          "transitive": 736,
          "total": 1210
        },
        {
          "path": "backend/tests/test_trader_orchestrator_worker.py",
          "direct": 305,
          "transitive": 732,
          "total": 1037
        },
        {
          "path": "backend/models/database.py",
          "direct": 199,
          "transitive": 732,
          "total": 931
        }
      ]
    },
    {
      "at": "2026-05-02T02:55:11.131Z",
      "sha": "7e62ec397c59c659b1d4c87978e30a315f3615bb",
      "pr": null,
      "actor": "braedonsaunders",
      "files": 855,
      "functions": 12459,
      "loc": 468001,
      "languages": 19,
      "topLanguages": [
        {
          "ext": "py",
          "pct": 76,
          "lines": 356194
        },
        {
          "ext": "tsx",
          "pct": 17,
          "lines": 78651
        },
        {
          "ext": "json",
          "pct": 3,
          "lines": 12990
        },
        {
          "ext": "ts",
          "pct": 3,
          "lines": 11717
        },
        {
          "ext": "md",
          "pct": 1,
          "lines": 3382
        }
      ],
      "dead": 109,
      "deadPct": 0.9,
      "circular": 1,
      "godObjects": 1,
      "avgCoupling": 8.4,
      "securityIssues": 69,
      "patterns": 12,
      "duplicates": 99,
      "layerViolations": 1403,
      "connections": 7210,
      "avgFnLines": 10.9,
      "longestFn": 16,
      "testFiles": 186,
      "testRatio": 21.8,
      "topFolders": [
        {
          "name": "backend",
          "count": 681
        },
        {
          "name": "frontend",
          "count": 141
        },
        {
          "name": "scripts",
          "count": 20
        },
        {
          "name": "root",
          "count": 7
        },
        {
          "name": "docs",
          "count": 3
        }
      ],
      "folders": 5,
      "grade": "D",
      "score": 60,
      "topBlast": {
        "path": "backend/services/strategy_helpers/persistent_state.py",
        "direct": 474,
        "transitive": 736,
        "total": 1210
      },
      "fragility": [
        {
          "path": "backend/services/strategy_helpers/persistent_state.py",
          "direct": 474,
          "transitive": 736,
          "total": 1210
        },
        {
          "path": "backend/tests/test_trader_orchestrator_worker.py",
          "direct": 305,
          "transitive": 732,
          "total": 1037
        },
        {
          "path": "backend/models/database.py",
          "direct": 199,
          "transitive": 732,
          "total": 931
        }
      ]
    },
    {
      "at": "2026-05-02T03:15:33.789Z",
      "sha": "622f432ddc61acf3c1507cc076864aa7afc482e2",
      "pr": null,
      "actor": "braedonsaunders",
      "files": 855,
      "functions": 12461,
      "loc": 468052,
      "languages": 19,
      "topLanguages": [
        {
          "ext": "py",
          "pct": 76,
          "lines": 356245
        },
        {
          "ext": "tsx",
          "pct": 17,
          "lines": 78651
        },
        {
          "ext": "json",
          "pct": 3,
          "lines": 12990
        },
        {
          "ext": "ts",
          "pct": 3,
          "lines": 11717
        },
        {
          "ext": "md",
          "pct": 1,
          "lines": 3382
        }
      ],
      "dead": 109,
      "deadPct": 0.9,
      "circular": 1,
      "godObjects": 1,
      "avgCoupling": 8.4,
      "securityIssues": 69,
      "patterns": 12,
      "duplicates": 99,
      "layerViolations": 1403,
      "connections": 7210,
      "avgFnLines": 10.9,
      "longestFn": 16,
      "testFiles": 186,
      "testRatio": 21.8,
      "topFolders": [
        {
          "name": "backend",
          "count": 681
        },
        {
          "name": "frontend",
          "count": 141
        },
        {
          "name": "scripts",
          "count": 20
        },
        {
          "name": "root",
          "count": 7
        },
        {
          "name": "docs",
          "count": 3
        }
      ],
      "folders": 5,
      "grade": "D",
      "score": 60,
      "topBlast": {
        "path": "backend/services/strategy_helpers/persistent_state.py",
        "direct": 474,
        "transitive": 736,
        "total": 1210
      },
      "fragility": [
        {
          "path": "backend/services/strategy_helpers/persistent_state.py",
          "direct": 474,
          "transitive": 736,
          "total": 1210
        },
        {
          "path": "backend/tests/test_trader_orchestrator_worker.py",
          "direct": 305,
          "transitive": 732,
          "total": 1037
        },
        {
          "path": "backend/models/database.py",
          "direct": 199,
          "transitive": 732,
          "total": 931
        }
      ]
    },
    {
      "at": "2026-05-02T05:04:38.138Z",
      "sha": "709170db9d14dd19d6d32ff16bdca261979e1ae4",
      "pr": null,
      "actor": "braedonsaunders",
      "files": 855,
      "functions": 12465,
      "loc": 468512,
      "languages": 19,
      "topLanguages": [
        {
          "ext": "py",
          "pct": 76,
          "lines": 356705
        },
        {
          "ext": "tsx",
          "pct": 17,
          "lines": 78651
        },
        {
          "ext": "json",
          "pct": 3,
          "lines": 12990
        },
        {
          "ext": "ts",
          "pct": 3,
          "lines": 11717
        },
        {
          "ext": "md",
          "pct": 1,
          "lines": 3382
        }
      ],
      "dead": 109,
      "deadPct": 0.9,
      "circular": 1,
      "godObjects": 1,
      "avgCoupling": 8.4,
      "securityIssues": 69,
      "patterns": 12,
      "duplicates": 99,
      "layerViolations": 1404,
      "connections": 7212,
      "avgFnLines": 10.9,
      "longestFn": 16,
      "testFiles": 186,
      "testRatio": 21.8,
      "topFolders": [
        {
          "name": "backend",
          "count": 681
        },
        {
          "name": "frontend",
          "count": 141
        },
        {
          "name": "scripts",
          "count": 20
        },
        {
          "name": "root",
          "count": 7
        },
        {
          "name": "docs",
          "count": 3
        }
      ],
      "folders": 5,
      "grade": "D",
      "score": 60,
      "topBlast": {
        "path": "backend/services/strategy_helpers/persistent_state.py",
        "direct": 475,
        "transitive": 736,
        "total": 1211
      },
      "fragility": [
        {
          "path": "backend/services/strategy_helpers/persistent_state.py",
          "direct": 475,
          "transitive": 736,
          "total": 1211
        },
        {
          "path": "backend/tests/test_trader_orchestrator_worker.py",
          "direct": 306,
          "transitive": 732,
          "total": 1038
        },
        {
          "path": "backend/models/database.py",
          "direct": 199,
          "transitive": 732,
          "total": 931
        }
      ]
    },
    {
      "at": "2026-05-02T15:37:35.620Z",
      "sha": "d1c579a20a042d67cd37ef60210f5cab99a9df92",
      "pr": null,
      "actor": "braedonsaunders",
      "files": 855,
      "functions": 12465,
      "loc": 468585,
      "languages": 19,
      "topLanguages": [
        {
          "ext": "py",
          "pct": 76,
          "lines": 356778
        },
        {
          "ext": "tsx",
          "pct": 17,
          "lines": 78651
        },
        {
          "ext": "json",
          "pct": 3,
          "lines": 12990
        },
        {
          "ext": "ts",
          "pct": 3,
          "lines": 11717
        },
        {
          "ext": "md",
          "pct": 1,
          "lines": 3382
        }
      ],
      "dead": 109,
      "deadPct": 0.9,
      "circular": 1,
      "godObjects": 1,
      "avgCoupling": 8.4,
      "securityIssues": 69,
      "patterns": 12,
      "duplicates": 99,
      "layerViolations": 1404,
      "connections": 7212,
      "avgFnLines": 10.9,
      "longestFn": 16,
      "testFiles": 186,
      "testRatio": 21.8,
      "topFolders": [
        {
          "name": "backend",
          "count": 681
        },
        {
          "name": "frontend",
          "count": 141
        },
        {
          "name": "scripts",
          "count": 20
        },
        {
          "name": "root",
          "count": 7
        },
        {
          "name": "docs",
          "count": 3
        }
      ],
      "folders": 5,
      "grade": "D",
      "score": 60,
      "topBlast": {
        "path": "backend/services/strategy_helpers/persistent_state.py",
        "direct": 475,
        "transitive": 736,
        "total": 1211
      },
      "fragility": [
        {
          "path": "backend/services/strategy_helpers/persistent_state.py",
          "direct": 475,
          "transitive": 736,
          "total": 1211
        },
        {
          "path": "backend/tests/test_trader_orchestrator_worker.py",
          "direct": 306,
          "transitive": 732,
          "total": 1038
        },
        {
          "path": "backend/models/database.py",
          "direct": 199,
          "transitive": 732,
          "total": 931
        }
      ]
    },
    {
      "at": "2026-05-02T15:49:11.317Z",
      "sha": "7242e7c5f53c00e2832d5e96d417923cb370bb00",
      "pr": null,
      "actor": "braedonsaunders",
      "files": 855,
      "functions": 12488,
      "loc": 470082,
      "languages": 19,
      "topLanguages": [
        {
          "ext": "py",
          "pct": 76,
          "lines": 356717
        },
        {
          "ext": "tsx",
          "pct": 17,
          "lines": 80209
        },
        {
          "ext": "json",
          "pct": 3,
          "lines": 12990
        },
        {
          "ext": "ts",
          "pct": 2,
          "lines": 11717
        },
        {
          "ext": "md",
          "pct": 1,
          "lines": 3382
        }
      ],
      "dead": 109,
      "deadPct": 0.9,
      "circular": 1,
      "godObjects": 1,
      "avgCoupling": 8.4,
      "securityIssues": 70,
      "patterns": 12,
      "duplicates": 99,
      "layerViolations": 1408,
      "connections": 7217,
      "avgFnLines": 10.9,
      "longestFn": 16,
      "testFiles": 186,
      "testRatio": 21.8,
      "topFolders": [
        {
          "name": "backend",
          "count": 681
        },
        {
          "name": "frontend",
          "count": 142
        },
        {
          "name": "scripts",
          "count": 19
        },
        {
          "name": "root",
          "count": 7
        },
        {
          "name": "docs",
          "count": 3
        }
      ],
      "folders": 5,
      "grade": "D",
      "score": 60,
      "topBlast": {
        "path": "backend/services/strategy_helpers/persistent_state.py",
        "direct": 475,
        "transitive": 738,
        "total": 1213
      },
      "fragility": [
        {
          "path": "backend/services/strategy_helpers/persistent_state.py",
          "direct": 475,
          "transitive": 738,
          "total": 1213
        },
        {
          "path": "backend/tests/test_trader_orchestrator_worker.py",
          "direct": 307,
          "transitive": 734,
          "total": 1041
        },
        {
          "path": "backend/models/database.py",
          "direct": 199,
          "transitive": 734,
          "total": 933
        }
      ]
    },
    {
      "at": "2026-05-02T16:02:11.501Z",
      "sha": "65130090e7643d8e9c0a888c93e92bb0e62d100d",
      "pr": null,
      "actor": "braedonsaunders",
      "files": 855,
      "functions": 12488,
      "loc": 470284,
      "languages": 19,
      "topLanguages": [
        {
          "ext": "py",
          "pct": 76,
          "lines": 356713
        },
        {
          "ext": "tsx",
          "pct": 17,
          "lines": 80415
        },
        {
          "ext": "json",
          "pct": 3,
          "lines": 12990
        },
        {
          "ext": "ts",
          "pct": 2,
          "lines": 11717
        },
        {
          "ext": "md",
          "pct": 1,
          "lines": 3382
        }
      ],
      "dead": 109,
      "deadPct": 0.9,
      "circular": 1,
      "godObjects": 1,
      "avgCoupling": 8.4,
      "securityIssues": 70,
      "patterns": 12,
      "duplicates": 99,
      "layerViolations": 1409,
      "connections": 7223,
      "avgFnLines": 10.9,
      "longestFn": 16,
      "testFiles": 186,
      "testRatio": 21.8,
      "topFolders": [
        {
          "name": "backend",
          "count": 681
        },
        {
          "name": "frontend",
          "count": 142
        },
        {
          "name": "scripts",
          "count": 19
        },
        {
          "name": "root",
          "count": 7
        },
        {
          "name": "docs",
          "count": 3
        }
      ],
      "folders": 5,
      "grade": "D",
      "score": 60,
      "topBlast": {
        "path": "backend/services/strategy_helpers/persistent_state.py",
        "direct": 475,
        "transitive": 738,
        "total": 1213
      },
      "fragility": [
        {
          "path": "backend/services/strategy_helpers/persistent_state.py",
          "direct": 475,
          "transitive": 738,
          "total": 1213
        },
        {
          "path": "backend/tests/test_trader_orchestrator_worker.py",
          "direct": 307,
          "transitive": 734,
          "total": 1041
        },
        {
          "path": "backend/models/database.py",
          "direct": 199,
          "transitive": 734,
          "total": 933
        }
      ]
    },
    {
      "at": "2026-05-02T17:55:36.847Z",
      "sha": "b815c6f7176acee970d4ec69cc5900c1e9f3c609",
      "pr": null,
      "actor": "braedonsaunders",
      "files": 860,
      "functions": 12541,
      "loc": 472856,
      "languages": 19,
      "topLanguages": [
        {
          "ext": "py",
          "pct": 76,
          "lines": 358868
        },
        {
          "ext": "tsx",
          "pct": 17,
          "lines": 80833
        },
        {
          "ext": "json",
          "pct": 3,
          "lines": 12892
        },
        {
          "ext": "ts",
          "pct": 2,
          "lines": 11806
        },
        {
          "ext": "md",
          "pct": 1,
          "lines": 3382
        }
      ],
      "dead": 108,
      "deadPct": 0.9,
      "circular": 1,
      "godObjects": 1,
      "avgCoupling": 8.4,
      "securityIssues": 70,
      "patterns": 13,
      "duplicates": 99,
      "layerViolations": 1414,
      "connections": 7258,
      "avgFnLines": 10.9,
      "longestFn": 16,
      "testFiles": 186,
      "testRatio": 21.6,
      "topFolders": [
        {
          "name": "backend",
          "count": 686
        },
        {
          "name": "frontend",
          "count": 142
        },
        {
          "name": "scripts",
          "count": 19
        },
        {
          "name": "root",
          "count": 7
        },
        {
          "name": "docs",
          "count": 3
        }
      ],
      "folders": 5,
      "grade": "D",
      "score": 60,
      "topBlast": {
        "path": "backend/services/strategy_helpers/persistent_state.py",
        "direct": 478,
        "transitive": 743,
        "total": 1221
      },
      "fragility": [
        {
          "path": "backend/services/strategy_helpers/persistent_state.py",
          "direct": 478,
          "transitive": 743,
          "total": 1221
        },
        {
          "path": "backend/tests/test_trader_orchestrator_worker.py",
          "direct": 308,
          "transitive": 736,
          "total": 1044
        },
        {
          "path": "backend/models/database.py",
          "direct": 200,
          "transitive": 736,
          "total": 936
        }
      ]
    },
    {
      "at": "2026-05-02T18:04:17.292Z",
      "sha": "a4a5cfe81cdbc15d0ccf319bf6f4166eaa802854",
      "pr": null,
      "actor": "braedonsaunders",
      "files": 860,
      "functions": 12532,
      "loc": 472701,
      "languages": 19,
      "topLanguages": [
        {
          "ext": "py",
          "pct": 76,
          "lines": 358713
        },
        {
          "ext": "tsx",
          "pct": 17,
          "lines": 80833
        },
        {
          "ext": "json",
          "pct": 3,
          "lines": 12892
        },
        {
          "ext": "ts",
          "pct": 2,
          "lines": 11806
        },
        {
          "ext": "md",
          "pct": 1,
          "lines": 3382
        }
      ],
      "dead": 108,
      "deadPct": 0.9,
      "circular": 1,
      "godObjects": 1,
      "avgCoupling": 8.4,
      "securityIssues": 70,
      "patterns": 12,
      "duplicates": 99,
      "layerViolations": 1414,
      "connections": 7254,
      "avgFnLines": 10.9,
      "longestFn": 16,
      "testFiles": 186,
      "testRatio": 21.6,
      "topFolders": [
        {
          "name": "backend",
          "count": 686
        },
        {
          "name": "frontend",
          "count": 142
        },
        {
          "name": "scripts",
          "count": 19
        },
        {
          "name": "root",
          "count": 7
        },
        {
          "name": "docs",
          "count": 3
        }
      ],
      "folders": 5,
      "grade": "D",
      "score": 60,
      "topBlast": {
        "path": "backend/services/strategy_helpers/persistent_state.py",
        "direct": 478,
        "transitive": 743,
        "total": 1221
      },
      "fragility": [
        {
          "path": "backend/services/strategy_helpers/persistent_state.py",
          "direct": 478,
          "transitive": 743,
          "total": 1221
        },
        {
          "path": "backend/tests/test_trader_orchestrator_worker.py",
          "direct": 308,
          "transitive": 736,
          "total": 1044
        },
        {
          "path": "backend/models/database.py",
          "direct": 200,
          "transitive": 736,
          "total": 936
        }
      ]
    },
    {
      "at": "2026-05-03T05:27:51.860Z",
      "sha": "675a0e0fa0b0c5a7a901f5213ebe3d081e720797",
      "pr": null,
      "actor": "braedonsaunders",
      "files": 860,
      "functions": 12532,
      "loc": 472771,
      "languages": 19,
      "topLanguages": [
        {
          "ext": "py",
          "pct": 76,
          "lines": 358713
        },
        {
          "ext": "tsx",
          "pct": 17,
          "lines": 80903
        },
        {
          "ext": "json",
          "pct": 3,
          "lines": 12892
        },
        {
          "ext": "ts",
          "pct": 2,
          "lines": 11806
        },
        {
          "ext": "md",
          "pct": 1,
          "lines": 3382
        }
      ],
      "dead": 108,
      "deadPct": 0.9,
      "circular": 1,
      "godObjects": 1,
      "avgCoupling": 8.4,
      "securityIssues": 70,
      "patterns": 12,
      "duplicates": 99,
      "layerViolations": 1414,
      "connections": 7253,
      "avgFnLines": 10.9,
      "longestFn": 16,
      "testFiles": 186,
      "testRatio": 21.6,
      "topFolders": [
        {
          "name": "backend",
          "count": 686
        },
        {
          "name": "frontend",
          "count": 142
        },
        {
          "name": "scripts",
          "count": 19
        },
        {
          "name": "root",
          "count": 7
        },
        {
          "name": "docs",
          "count": 3
        }
      ],
      "folders": 5,
      "grade": "D",
      "score": 60,
      "topBlast": {
        "path": "backend/services/strategy_helpers/persistent_state.py",
        "direct": 478,
        "transitive": 743,
        "total": 1221
      },
      "fragility": [
        {
          "path": "backend/services/strategy_helpers/persistent_state.py",
          "direct": 478,
          "transitive": 743,
          "total": 1221
        },
        {
          "path": "backend/tests/test_trader_orchestrator_worker.py",
          "direct": 308,
          "transitive": 736,
          "total": 1044
        },
        {
          "path": "backend/models/database.py",
          "direct": 200,
          "transitive": 736,
          "total": 936
        }
      ]
    },
    {
      "at": "2026-05-03T06:28:33.801Z",
      "sha": "e6c78e9d5881469c212ae94dced60910ac8fc533",
      "pr": null,
      "actor": "braedonsaunders",
      "files": 862,
      "functions": 12586,
      "loc": 474527,
      "languages": 19,
      "topLanguages": [
        {
          "ext": "py",
          "pct": 76,
          "lines": 360469
        },
        {
          "ext": "tsx",
          "pct": 17,
          "lines": 80903
        },
        {
          "ext": "json",
          "pct": 3,
          "lines": 12892
        },
        {
          "ext": "ts",
          "pct": 2,
          "lines": 11806
        },
        {
          "ext": "md",
          "pct": 1,
          "lines": 3382
        }
      ],
      "dead": 110,
      "deadPct": 0.9,
      "circular": 1,
      "godObjects": 1,
      "avgCoupling": 8.4,
      "securityIssues": 70,
      "patterns": 12,
      "duplicates": 99,
      "layerViolations": 1417,
      "connections": 7276,
      "avgFnLines": 10.9,
      "longestFn": 16,
      "testFiles": 187,
      "testRatio": 21.7,
      "topFolders": [
        {
          "name": "backend",
          "count": 688
        },
        {
          "name": "frontend",
          "count": 142
        },
        {
          "name": "scripts",
          "count": 19
        },
        {
          "name": "root",
          "count": 7
        },
        {
          "name": "docs",
          "count": 3
        }
      ],
      "folders": 5,
      "grade": "D",
      "score": 60,
      "topBlast": {
        "path": "backend/services/strategy_helpers/persistent_state.py",
        "direct": 480,
        "transitive": 745,
        "total": 1225
      },
      "fragility": [
        {
          "path": "backend/services/strategy_helpers/persistent_state.py",
          "direct": 480,
          "transitive": 745,
          "total": 1225
        },
        {
          "path": "backend/tests/test_trader_orchestrator_worker.py",
          "direct": 309,
          "transitive": 738,
          "total": 1047
        },
        {
          "path": "backend/models/database.py",
          "direct": 200,
          "transitive": 738,
          "total": 938
        }
      ]
    },
    {
      "at": "2026-05-03T06:46:09.296Z",
      "sha": "26fd150151f51aa91cf4197fb462366f711d2062",
      "pr": null,
      "actor": "braedonsaunders",
      "files": 862,
      "functions": 12586,
      "loc": 475253,
      "languages": 19,
      "topLanguages": [
        {
          "ext": "py",
          "pct": 76,
          "lines": 360467
        },
        {
          "ext": "tsx",
          "pct": 17,
          "lines": 80987
        },
        {
          "ext": "json",
          "pct": 3,
          "lines": 12892
        },
        {
          "ext": "ts",
          "pct": 2,
          "lines": 11806
        },
        {
          "ext": "md",
          "pct": 1,
          "lines": 3386
        }
      ],
      "dead": 110,
      "deadPct": 0.9,
      "circular": 1,
      "godObjects": 1,
      "avgCoupling": 8.4,
      "securityIssues": 70,
      "patterns": 12,
      "duplicates": 99,
      "layerViolations": 1417,
      "connections": 7276,
      "avgFnLines": 10.9,
      "longestFn": 16,
      "testFiles": 187,
      "testRatio": 21.7,
      "topFolders": [
        {
          "name": "backend",
          "count": 688
        },
        {
          "name": "frontend",
          "count": 142
        },
        {
          "name": "scripts",
          "count": 19
        },
        {
          "name": "root",
          "count": 7
        },
        {
          "name": "docs",
          "count": 3
        }
      ],
      "folders": 5,
      "grade": "D",
      "score": 60,
      "topBlast": {
        "path": "backend/services/strategy_helpers/persistent_state.py",
        "direct": 480,
        "transitive": 745,
        "total": 1225
      },
      "fragility": [
        {
          "path": "backend/services/strategy_helpers/persistent_state.py",
          "direct": 480,
          "transitive": 745,
          "total": 1225
        },
        {
          "path": "backend/tests/test_trader_orchestrator_worker.py",
          "direct": 309,
          "transitive": 738,
          "total": 1047
        },
        {
          "path": "backend/models/database.py",
          "direct": 200,
          "transitive": 738,
          "total": 938
        }
      ]
    },
    {
      "at": "2026-05-03T06:49:10.641Z",
      "sha": "107e6ebf4a66b451daaaee7a92fd3272827039af",
      "pr": null,
      "actor": "braedonsaunders",
      "files": 862,
      "functions": 12586,
      "loc": 475258,
      "languages": 19,
      "topLanguages": [
        {
          "ext": "py",
          "pct": 76,
          "lines": 360467
        },
        {
          "ext": "tsx",
          "pct": 17,
          "lines": 80992
        },
        {
          "ext": "json",
          "pct": 3,
          "lines": 12892
        },
        {
          "ext": "ts",
          "pct": 2,
          "lines": 11806
        },
        {
          "ext": "md",
          "pct": 1,
          "lines": 3386
        }
      ],
      "dead": 110,
      "deadPct": 0.9,
      "circular": 1,
      "godObjects": 1,
      "avgCoupling": 8.4,
      "securityIssues": 70,
      "patterns": 12,
      "duplicates": 99,
      "layerViolations": 1417,
      "connections": 7276,
      "avgFnLines": 10.9,
      "longestFn": 16,
      "testFiles": 187,
      "testRatio": 21.7,
      "topFolders": [
        {
          "name": "backend",
          "count": 688
        },
        {
          "name": "frontend",
          "count": 142
        },
        {
          "name": "scripts",
          "count": 19
        },
        {
          "name": "root",
          "count": 7
        },
        {
          "name": "docs",
          "count": 3
        }
      ],
      "folders": 5,
      "grade": "D",
      "score": 60,
      "topBlast": {
        "path": "backend/services/strategy_helpers/persistent_state.py",
        "direct": 480,
        "transitive": 745,
        "total": 1225
      },
      "fragility": [
        {
          "path": "backend/services/strategy_helpers/persistent_state.py",
          "direct": 480,
          "transitive": 745,
          "total": 1225
        },
        {
          "path": "backend/tests/test_trader_orchestrator_worker.py",
          "direct": 309,
          "transitive": 738,
          "total": 1047
        },
        {
          "path": "backend/models/database.py",
          "direct": 200,
          "transitive": 738,
          "total": 938
        }
      ]
    },
    {
      "at": "2026-05-03T07:31:27.712Z",
      "sha": "4493734ee91f8bb960d7c167a69f49c55d677a6b",
      "pr": null,
      "actor": "braedonsaunders",
      "files": 862,
      "functions": 12586,
      "loc": 475365,
      "languages": 19,
      "topLanguages": [
        {
          "ext": "py",
          "pct": 76,
          "lines": 360574
        },
        {
          "ext": "tsx",
          "pct": 17,
          "lines": 80992
        },
        {
          "ext": "json",
          "pct": 3,
          "lines": 12892
        },
        {
          "ext": "ts",
          "pct": 2,
          "lines": 11806
        },
        {
          "ext": "md",
          "pct": 1,
          "lines": 3386
        }
      ],
      "dead": 110,
      "deadPct": 0.9,
      "circular": 1,
      "godObjects": 1,
      "avgCoupling": 8.4,
      "securityIssues": 70,
      "patterns": 12,
      "duplicates": 99,
      "layerViolations": 1417,
      "connections": 7278,
      "avgFnLines": 10.9,
      "longestFn": 16,
      "testFiles": 187,
      "testRatio": 21.7,
      "topFolders": [
        {
          "name": "backend",
          "count": 688
        },
        {
          "name": "frontend",
          "count": 142
        },
        {
          "name": "scripts",
          "count": 19
        },
        {
          "name": "root",
          "count": 7
        },
        {
          "name": "docs",
          "count": 3
        }
      ],
      "folders": 5,
      "grade": "D",
      "score": 60,
      "topBlast": {
        "path": "backend/services/strategy_helpers/persistent_state.py",
        "direct": 480,
        "transitive": 745,
        "total": 1225
      },
      "fragility": [
        {
          "path": "backend/services/strategy_helpers/persistent_state.py",
          "direct": 480,
          "transitive": 745,
          "total": 1225
        },
        {
          "path": "backend/tests/test_trader_orchestrator_worker.py",
          "direct": 309,
          "transitive": 738,
          "total": 1047
        },
        {
          "path": "backend/models/database.py",
          "direct": 200,
          "transitive": 738,
          "total": 938
        }
      ]
    },
    {
      "at": "2026-05-03T16:41:24.407Z",
      "sha": "98f391a05140eaf13531a48134cfb92f67683538",
      "pr": null,
      "actor": "braedonsaunders",
      "files": 862,
      "functions": 12589,
      "loc": 475506,
      "languages": 19,
      "topLanguages": [
        {
          "ext": "py",
          "pct": 76,
          "lines": 360676
        },
        {
          "ext": "tsx",
          "pct": 17,
          "lines": 80992
        },
        {
          "ext": "json",
          "pct": 3,
          "lines": 12931
        },
        {
          "ext": "ts",
          "pct": 2,
          "lines": 11806
        },
        {
          "ext": "md",
          "pct": 1,
          "lines": 3386
        }
      ],
      "dead": 110,
      "deadPct": 0.9,
      "circular": 1,
      "godObjects": 1,
      "avgCoupling": 8.4,
      "securityIssues": 70,
      "patterns": 12,
      "duplicates": 99,
      "layerViolations": 1417,
      "connections": 7279,
      "avgFnLines": 10.9,
      "longestFn": 16,
      "testFiles": 187,
      "testRatio": 21.7,
      "topFolders": [
        {
          "name": "backend",
          "count": 688
        },
        {
          "name": "frontend",
          "count": 142
        },
        {
          "name": "scripts",
          "count": 19
        },
        {
          "name": "root",
          "count": 7
        },
        {
          "name": "docs",
          "count": 3
        }
      ],
      "folders": 5,
      "grade": "D",
      "score": 60,
      "topBlast": {
        "path": "backend/services/strategy_helpers/persistent_state.py",
        "direct": 480,
        "transitive": 745,
        "total": 1225
      },
      "fragility": [
        {
          "path": "backend/services/strategy_helpers/persistent_state.py",
          "direct": 480,
          "transitive": 745,
          "total": 1225
        },
        {
          "path": "backend/tests/test_trader_orchestrator_worker.py",
          "direct": 310,
          "transitive": 738,
          "total": 1048
        },
        {
          "path": "backend/models/database.py",
          "direct": 200,
          "transitive": 738,
          "total": 938
        }
      ]
    },
    {
      "at": "2026-05-03T17:01:29.163Z",
      "sha": "976d1231a03b2a0c85ae460ac36289356e0e24cf",
      "pr": null,
      "actor": "braedonsaunders",
      "files": 862,
      "functions": 12589,
      "loc": 475556,
      "languages": 19,
      "topLanguages": [
        {
          "ext": "py",
          "pct": 76,
          "lines": 360716
        },
        {
          "ext": "tsx",
          "pct": 17,
          "lines": 80992
        },
        {
          "ext": "json",
          "pct": 3,
          "lines": 12931
        },
        {
          "ext": "ts",
          "pct": 2,
          "lines": 11806
        },
        {
          "ext": "md",
          "pct": 1,
          "lines": 3386
        }
      ],
      "dead": 110,
      "deadPct": 0.9,
      "circular": 1,
      "godObjects": 1,
      "avgCoupling": 8.4,
      "securityIssues": 70,
      "patterns": 12,
      "duplicates": 99,
      "layerViolations": 1417,
      "connections": 7279,
      "avgFnLines": 10.9,
      "longestFn": 16,
      "testFiles": 187,
      "testRatio": 21.7,
      "topFolders": [
        {
          "name": "backend",
          "count": 688
        },
        {
          "name": "frontend",
          "count": 142
        },
        {
          "name": "scripts",
          "count": 19
        },
        {
          "name": "root",
          "count": 7
        },
        {
          "name": "docs",
          "count": 3
        }
      ],
      "folders": 5,
      "grade": "D",
      "score": 60,
      "topBlast": {
        "path": "backend/services/strategy_helpers/persistent_state.py",
        "direct": 480,
        "transitive": 745,
        "total": 1225
      },
      "fragility": [
        {
          "path": "backend/services/strategy_helpers/persistent_state.py",
          "direct": 480,
          "transitive": 745,
          "total": 1225
        },
        {
          "path": "backend/tests/test_trader_orchestrator_worker.py",
          "direct": 310,
          "transitive": 738,
          "total": 1048
        },
        {
          "path": "backend/models/database.py",
          "direct": 200,
          "transitive": 738,
          "total": 938
        }
      ]
    },
    {
      "at": "2026-05-03T18:25:03.546Z",
      "sha": "d544ba29131dc1f7a00cd0d70a5601602df9b323",
      "pr": null,
      "actor": "braedonsaunders",
      "files": 862,
      "functions": 12590,
      "loc": 475789,
      "languages": 19,
      "topLanguages": [
        {
          "ext": "py",
          "pct": 76,
          "lines": 360949
        },
        {
          "ext": "tsx",
          "pct": 17,
          "lines": 80992
        },
        {
          "ext": "json",
          "pct": 3,
          "lines": 12931
        },
        {
          "ext": "ts",
          "pct": 2,
          "lines": 11806
        },
        {
          "ext": "md",
          "pct": 1,
          "lines": 3386
        }
      ],
      "dead": 110,
      "deadPct": 0.9,
      "circular": 1,
      "godObjects": 1,
      "avgCoupling": 8.4,
      "securityIssues": 70,
      "patterns": 12,
      "duplicates": 99,
      "layerViolations": 1418,
      "connections": 7280,
      "avgFnLines": 10.9,
      "longestFn": 16,
      "testFiles": 187,
      "testRatio": 21.7,
      "topFolders": [
        {
          "name": "backend",
          "count": 688
        },
        {
          "name": "frontend",
          "count": 142
        },
        {
          "name": "scripts",
          "count": 19
        },
        {
          "name": "root",
          "count": 7
        },
        {
          "name": "docs",
          "count": 3
        }
      ],
      "folders": 5,
      "grade": "D",
      "score": 60,
      "topBlast": {
        "path": "backend/services/strategy_helpers/persistent_state.py",
        "direct": 480,
        "transitive": 745,
        "total": 1225
      },
      "fragility": [
        {
          "path": "backend/services/strategy_helpers/persistent_state.py",
          "direct": 480,
          "transitive": 745,
          "total": 1225
        },
        {
          "path": "backend/tests/test_trader_orchestrator_worker.py",
          "direct": 311,
          "transitive": 738,
          "total": 1049
        },
        {
          "path": "backend/models/database.py",
          "direct": 200,
          "transitive": 738,
          "total": 938
        }
      ]
    },
    {
      "at": "2026-05-03T18:30:05.537Z",
      "sha": "cb46ff2c9b1aec019aec8106db82d8bd9899f0a2",
      "pr": null,
      "actor": "braedonsaunders",
      "files": 867,
      "functions": 12590,
      "loc": 476305,
      "languages": 22,
      "topLanguages": [
        {
          "ext": "py",
          "pct": 76,
          "lines": 360949
        },
        {
          "ext": "tsx",
          "pct": 17,
          "lines": 80992
        },
        {
          "ext": "json",
          "pct": 3,
          "lines": 12931
        },
        {
          "ext": "ts",
          "pct": 2,
          "lines": 11806
        },
        {
          "ext": "md",
          "pct": 1,
          "lines": 3399
        }
      ],
      "dead": 110,
      "deadPct": 0.9,
      "circular": 1,
      "godObjects": 1,
      "avgCoupling": 8.4,
      "securityIssues": 70,
      "patterns": 12,
      "duplicates": 99,
      "layerViolations": 1418,
      "connections": 7282,
      "avgFnLines": 10.9,
      "longestFn": 16,
      "testFiles": 187,
      "testRatio": 21.6,
      "topFolders": [
        {
          "name": "backend",
          "count": 689
        },
        {
          "name": "frontend",
          "count": 144
        },
        {
          "name": "scripts",
          "count": 19
        },
        {
          "name": "root",
          "count": 9
        },
        {
          "name": "docs",
          "count": 3
        }
      ],
      "folders": 5,
      "grade": "D",
      "score": 60,
      "topBlast": {
        "path": "backend/services/strategy_helpers/persistent_state.py",
        "direct": 480,
        "transitive": 747,
        "total": 1227
      },
      "fragility": [
        {
          "path": "backend/services/strategy_helpers/persistent_state.py",
          "direct": 480,
          "transitive": 747,
          "total": 1227
        },
        {
          "path": "backend/tests/test_trader_orchestrator_worker.py",
          "direct": 311,
          "transitive": 740,
          "total": 1051
        },
        {
          "path": "backend/models/database.py",
          "direct": 200,
          "transitive": 740,
          "total": 940
        }
      ]
    },
    {
      "at": "2026-05-03T19:22:00.487Z",
      "sha": "089d004fb3edbc29b85e8d49a408b8df4b4103ca",
      "pr": null,
      "actor": "braedonsaunders",
      "files": 867,
      "functions": 12602,
      "loc": 476457,
      "languages": 22,
      "topLanguages": [
        {
          "ext": "py",
          "pct": 76,
          "lines": 361101
        },
        {
          "ext": "tsx",
          "pct": 17,
          "lines": 80992
        },
        {
          "ext": "json",
          "pct": 3,
          "lines": 12931
        },
        {
          "ext": "ts",
          "pct": 2,
          "lines": 11806
        },
        {
          "ext": "md",
          "pct": 1,
          "lines": 3399
        }
      ],
      "dead": 110,
      "deadPct": 0.9,
      "circular": 1,
      "godObjects": 1,
      "avgCoupling": 8.4,
      "securityIssues": 70,
      "patterns": 12,
      "duplicates": 99,
      "layerViolations": 1418,
      "connections": 7282,
      "avgFnLines": 10.9,
      "longestFn": 16,
      "testFiles": 187,
      "testRatio": 21.6,
      "topFolders": [
        {
          "name": "backend",
          "count": 689
        },
        {
          "name": "frontend",
          "count": 144
        },
        {
          "name": "scripts",
          "count": 19
        },
        {
          "name": "root",
          "count": 9
        },
        {
          "name": "docs",
          "count": 3
        }
      ],
      "folders": 5,
      "grade": "D",
      "score": 60,
      "topBlast": {
        "path": "backend/services/strategy_helpers/persistent_state.py",
        "direct": 480,
        "transitive": 747,
        "total": 1227
      },
      "fragility": [
        {
          "path": "backend/services/strategy_helpers/persistent_state.py",
          "direct": 480,
          "transitive": 747,
          "total": 1227
        },
        {
          "path": "backend/tests/test_trader_orchestrator_worker.py",
          "direct": 311,
          "transitive": 740,
          "total": 1051
        },
        {
          "path": "backend/models/database.py",
          "direct": 200,
          "transitive": 740,
          "total": 940
        }
      ]
    },
    {
      "at": "2026-05-03T19:25:41.705Z",
      "sha": "fe0ea8ac3372e41bb8210accc0efe30d6c4a8296",
      "pr": null,
      "actor": "braedonsaunders",
      "files": 867,
      "functions": 12602,
      "loc": 476498,
      "languages": 22,
      "topLanguages": [
        {
          "ext": "py",
          "pct": 76,
          "lines": 361118
        },
        {
          "ext": "tsx",
          "pct": 17,
          "lines": 80992
        },
        {
          "ext": "json",
          "pct": 3,
          "lines": 12931
        },
        {
          "ext": "ts",
          "pct": 2,
          "lines": 11806
        },
        {
          "ext": "md",
          "pct": 1,
          "lines": 3399
        }
      ],
      "dead": 110,
      "deadPct": 0.9,
      "circular": 1,
      "godObjects": 1,
      "avgCoupling": 8.4,
      "securityIssues": 70,
      "patterns": 12,
      "duplicates": 99,
      "layerViolations": 1418,
      "connections": 7284,
      "avgFnLines": 10.9,
      "longestFn": 16,
      "testFiles": 187,
      "testRatio": 21.6,
      "topFolders": [
        {
          "name": "backend",
          "count": 689
        },
        {
          "name": "frontend",
          "count": 144
        },
        {
          "name": "scripts",
          "count": 19
        },
        {
          "name": "root",
          "count": 9
        },
        {
          "name": "docs",
          "count": 3
        }
      ],
      "folders": 5,
      "grade": "D",
      "score": 60,
      "topBlast": {
        "path": "backend/services/strategy_helpers/persistent_state.py",
        "direct": 480,
        "transitive": 747,
        "total": 1227
      },
      "fragility": [
        {
          "path": "backend/services/strategy_helpers/persistent_state.py",
          "direct": 480,
          "transitive": 747,
          "total": 1227
        },
        {
          "path": "backend/tests/test_trader_orchestrator_worker.py",
          "direct": 311,
          "transitive": 740,
          "total": 1051
        },
        {
          "path": "backend/models/database.py",
          "direct": 201,
          "transitive": 740,
          "total": 941
        }
      ]
    },
    {
      "at": "2026-05-03T20:11:49.627Z",
      "sha": "cba999e0f7103083ede4f6c5ab9d649f5eafab9d",
      "pr": null,
      "actor": "braedonsaunders",
      "files": 867,
      "functions": 12603,
      "loc": 476774,
      "languages": 22,
      "topLanguages": [
        {
          "ext": "py",
          "pct": 76,
          "lines": 361394
        },
        {
          "ext": "tsx",
          "pct": 17,
          "lines": 80992
        },
        {
          "ext": "json",
          "pct": 3,
          "lines": 12931
        },
        {
          "ext": "ts",
          "pct": 2,
          "lines": 11806
        },
        {
          "ext": "md",
          "pct": 1,
          "lines": 3399
        }
      ],
      "dead": 110,
      "deadPct": 0.9,
      "circular": 1,
      "godObjects": 1,
      "avgCoupling": 8.4,
      "securityIssues": 70,
      "patterns": 12,
      "duplicates": 99,
      "layerViolations": 1418,
      "connections": 7284,
      "avgFnLines": 10.9,
      "longestFn": 16,
      "testFiles": 187,
      "testRatio": 21.6,
      "topFolders": [
        {
          "name": "backend",
          "count": 689
        },
        {
          "name": "frontend",
          "count": 144
        },
        {
          "name": "scripts",
          "count": 19
        },
        {
          "name": "root",
          "count": 9
        },
        {
          "name": "docs",
          "count": 3
        }
      ],
      "folders": 5,
      "grade": "D",
      "score": 60,
      "topBlast": {
        "path": "backend/services/strategy_helpers/persistent_state.py",
        "direct": 480,
        "transitive": 747,
        "total": 1227
      },
      "fragility": [
        {
          "path": "backend/services/strategy_helpers/persistent_state.py",
          "direct": 480,
          "transitive": 747,
          "total": 1227
        },
        {
          "path": "backend/tests/test_trader_orchestrator_worker.py",
          "direct": 311,
          "transitive": 740,
          "total": 1051
        },
        {
          "path": "backend/models/database.py",
          "direct": 201,
          "transitive": 740,
          "total": 941
        }
      ]
    },
    {
      "at": "2026-05-03T20:47:07.747Z",
      "sha": "41a63d7af0f753d6f21e7381346ab91e2db4fdeb",
      "pr": null,
      "actor": "braedonsaunders",
      "files": 867,
      "functions": 12603,
      "loc": 476877,
      "languages": 22,
      "topLanguages": [
        {
          "ext": "py",
          "pct": 76,
          "lines": 361497
        },
        {
          "ext": "tsx",
          "pct": 17,
          "lines": 80992
        },
        {
          "ext": "json",
          "pct": 3,
          "lines": 12931
        },
        {
          "ext": "ts",
          "pct": 2,
          "lines": 11806
        },
        {
          "ext": "md",
          "pct": 1,
          "lines": 3399
        }
      ],
      "dead": 110,
      "deadPct": 0.9,
      "circular": 1,
      "godObjects": 1,
      "avgCoupling": 8.4,
      "securityIssues": 70,
      "patterns": 12,
      "duplicates": 99,
      "layerViolations": 1418,
      "connections": 7284,
      "avgFnLines": 10.9,
      "longestFn": 16,
      "testFiles": 187,
      "testRatio": 21.6,
      "topFolders": [
        {
          "name": "backend",
          "count": 689
        },
        {
          "name": "frontend",
          "count": 144
        },
        {
          "name": "scripts",
          "count": 19
        },
        {
          "name": "root",
          "count": 9
        },
        {
          "name": "docs",
          "count": 3
        }
      ],
      "folders": 5,
      "grade": "D",
      "score": 60,
      "topBlast": {
        "path": "backend/services/strategy_helpers/persistent_state.py",
        "direct": 480,
        "transitive": 747,
        "total": 1227
      },
      "fragility": [
        {
          "path": "backend/services/strategy_helpers/persistent_state.py",
          "direct": 480,
          "transitive": 747,
          "total": 1227
        },
        {
          "path": "backend/tests/test_trader_orchestrator_worker.py",
          "direct": 311,
          "transitive": 740,
          "total": 1051
        },
        {
          "path": "backend/models/database.py",
          "direct": 201,
          "transitive": 740,
          "total": 941
        }
      ]
    },
    {
      "at": "2026-05-03T22:40:50.882Z",
      "sha": "42cad795c7ca7ff1fd3d09e713282f86c1d5afd9",
      "pr": null,
      "actor": "braedonsaunders",
      "files": 868,
      "functions": 12607,
      "loc": 477197,
      "languages": 22,
      "topLanguages": [
        {
          "ext": "py",
          "pct": 76,
          "lines": 361817
        },
        {
          "ext": "tsx",
          "pct": 17,
          "lines": 80992
        },
        {
          "ext": "json",
          "pct": 3,
          "lines": 12931
        },
        {
          "ext": "ts",
          "pct": 2,
          "lines": 11806
        },
        {
          "ext": "md",
          "pct": 1,
          "lines": 3399
        }
      ],
      "dead": 110,
      "deadPct": 0.9,
      "circular": 1,
      "godObjects": 1,
      "avgCoupling": 8.4,
      "securityIssues": 70,
      "patterns": 12,
      "duplicates": 99,
      "layerViolations": 1421,
      "connections": 7287,
      "avgFnLines": 10.9,
      "longestFn": 16,
      "testFiles": 187,
      "testRatio": 21.5,
      "topFolders": [
        {
          "name": "backend",
          "count": 690
        },
        {
          "name": "frontend",
          "count": 144
        },
        {
          "name": "scripts",
          "count": 19
        },
        {
          "name": "root",
          "count": 9
        },
        {
          "name": "docs",
          "count": 3
        }
      ],
      "folders": 5,
      "grade": "D",
      "score": 60,
      "topBlast": {
        "path": "backend/services/strategy_helpers/persistent_state.py",
        "direct": 480,
        "transitive": 748,
        "total": 1228
      },
      "fragility": [
        {
          "path": "backend/services/strategy_helpers/persistent_state.py",
          "direct": 480,
          "transitive": 748,
          "total": 1228
        },
        {
          "path": "backend/tests/test_trader_orchestrator_worker.py",
          "direct": 312,
          "transitive": 741,
          "total": 1053
        },
        {
          "path": "backend/models/database.py",
          "direct": 201,
          "transitive": 741,
          "total": 942
        }
      ]
    },
    {
      "at": "2026-05-03T22:53:29.260Z",
      "sha": "d1c2dc308022ecc8bedb6b53d6901672d91fb4b4",
      "pr": null,
      "actor": "braedonsaunders",
      "files": 868,
      "functions": 12607,
      "loc": 477203,
      "languages": 22,
      "topLanguages": [
        {
          "ext": "py",
          "pct": 76,
          "lines": 361823
        },
        {
          "ext": "tsx",
          "pct": 17,
          "lines": 80992
        },
        {
          "ext": "json",
          "pct": 3,
          "lines": 12931
        },
        {
          "ext": "ts",
          "pct": 2,
          "lines": 11806
        },
        {
          "ext": "md",
          "pct": 1,
          "lines": 3399
        }
      ],
      "dead": 110,
      "deadPct": 0.9,
      "circular": 1,
      "godObjects": 1,
      "avgCoupling": 8.4,
      "securityIssues": 70,
      "patterns": 12,
      "duplicates": 99,
      "layerViolations": 1421,
      "connections": 7287,
      "avgFnLines": 10.9,
      "longestFn": 16,
      "testFiles": 187,
      "testRatio": 21.5,
      "topFolders": [
        {
          "name": "backend",
          "count": 690
        },
        {
          "name": "frontend",
          "count": 144
        },
        {
          "name": "scripts",
          "count": 19
        },
        {
          "name": "root",
          "count": 9
        },
        {
          "name": "docs",
          "count": 3
        }
      ],
      "folders": 5,
      "grade": "D",
      "score": 60,
      "topBlast": {
        "path": "backend/services/strategy_helpers/persistent_state.py",
        "direct": 480,
        "transitive": 748,
        "total": 1228
      },
      "fragility": [
        {
          "path": "backend/services/strategy_helpers/persistent_state.py",
          "direct": 480,
          "transitive": 748,
          "total": 1228
        },
        {
          "path": "backend/tests/test_trader_orchestrator_worker.py",
          "direct": 312,
          "transitive": 741,
          "total": 1053
        },
        {
          "path": "backend/models/database.py",
          "direct": 201,
          "transitive": 741,
          "total": 942
        }
      ]
    }
  ]
}
